basic_flask/__init__.py
basic_flask/create_flask.py
basic_flask/creation_files/__init__.py
basic_flask/creation_files/activate_this.py
basic_flask/creation_files/main.py
basic_flask-0.1.1.dist-info/LICENSE
basic_flask-0.1.1.dist-info/METADATA
basic_flask-0.1.1.dist-info/WHEEL
basic_flask-0.1.1.dist-info/entry_points.txt
basic_flask-0.1.1.dist-info/top_level.txt
basic_flask-0.1.1.dist-info/RECORD
