Metadata-Version: 2.1
Name: basic-flask
Version: 0.1.1
Summary: A packge to create a simple flask app in a single commend
Home-page: https://github.com/omercotkd/basic-flask
Author: omer cohen
Author-email: omerco.python@gmail.com
License: UNKNOWN
Project-URL: Bug Tracker, https://github.com/omercotkd/basic-flask
Platform: UNKNOWN
Classifier: Programming Language :: Python :: 3
Classifier: License :: OSI Approved :: MIT License
Classifier: Operating System :: OS Independent
Requires-Python: >=3.6
License-File: LICENSE
